{"name":"UCOB GNB","sets":[{"name":"2.40 - BIS","items":{"Weapon":{"id":33477,"materia":[],"relicStats":{"dhit":0,"crit":127,"tenacity":89,"determination":125,"skillspeed":127}},"Head":{"id":19375,"materia":[{"id":18019,"locked":false},{"id":18018,"locked":false}]},"Body":{"id":10000000725157,"materia":[]},"Hand":{"id":10000000725158,"materia":[]},"Legs":{"id":10000000725159,"materia":[]},"Feet":{"id":22752,"materia":[{"id":18018,"locked":false},{"id":18020,"locked":false}]},"Ears":{"id":10000000725161,"materia":[]},"Neck":{"id":10000000725162,"materia":[]},"Wrist":{"id":10000000725163,"materia":[]},"RingLeft":{"id":10000000725164,"materia":[]},"RingRight":{"id":10000000725164,"materia":[]}},"food":46003,"description":"Traditionally used speed throughout history","isSeparator":false,"relicStatMemory":{},"materiaMemory":{"Head":[[19375,[18019,-1],[false,false]]],"Feet":[[22752,[18018,18018],[false,false]]]}},{"name":"2.45 - BIS","items":{"Weapon":{"id":33477,"materia":[],"relicStats":{"dhit":0,"crit":126,"tenacity":97,"determination":127,"skillspeed":118}},"Head":{"id":10000000725156,"materia":[]},"Body":{"id":10000000725157,"materia":[]},"Hand":{"id":10000000725158,"materia":[]},"Legs":{"id":10000000725159,"materia":[]},"Feet":{"id":19301,"materia":[{"id":18019,"locked":false},{"id":18018,"locked":false}]},"Ears":{"id":10000000725161,"materia":[]},"Neck":{"id":10000000725162,"materia":[]},"Wrist":{"id":10000000725163,"materia":[]},"RingLeft":{"id":10000000725164,"materia":[]},"RingRight":{"id":10000000725164,"materia":[]}},"food":46003,"description":"Most optimal distribution of relic and food stats (less SKS gear means more DET food utilization), but historically not a commonly used or mainstreamed GCD speed for UCOB (doesn't mean it's worse, just not confirmed to be any better)\n\nOnly listing this speed because it makes better use of the gear, up to you to decide if it works better for you in instance or not","isSeparator":false,"relicStatMemory":{},"materiaMemory":{"Wrist":[[19349,[-1],[false]]],"Neck":[[19422,[18018],[false]]],"Feet":[[19301,[-1,-1],[false,false]]]}},{"name":"2.40 - Sync","items":{"Weapon":{"id":33477,"materia":[],"relicStats":{"dhit":0,"crit":127,"tenacity":97,"determination":125,"skillspeed":119}},"Head":{"id":10000000725156,"materia":[]},"Body":{"id":10000000725157,"materia":[]},"Hand":{"id":10000000725166,"materia":[]},"Legs":{"id":10000000725159,"materia":[]},"Feet":{"id":10000000725160,"materia":[]},"Ears":{"id":10000000725161,"materia":[]},"Neck":{"id":10000000725165,"materia":[]},"Wrist":{"id":10000000725163,"materia":[]},"RingLeft":{"id":10000000725164,"materia":[]},"RingRight":{"id":10000000725164,"materia":[]}},"food":46003,"description":"","isSeparator":false,"relicStatMemory":{},"materiaMemory":{"RingLeft":[[22805,[-1],[false]]],"Ears":[[19339,[-1],[false]]]}},{"name":"2.45 - Sync","items":{"Weapon":{"id":33477,"materia":[],"relicStats":{"dhit":0,"crit":126,"tenacity":97,"determination":127,"skillspeed":118}},"Head":{"id":10000000725156,"materia":[]},"Body":{"id":10000000725157,"materia":[]},"Hand":{"id":10000000725158,"materia":[]},"Legs":{"id":10000000725159,"materia":[]},"Feet":{"id":10000000725160,"materia":[]},"Ears":{"id":10000000725161,"materia":[]},"Neck":{"id":10000000725162,"materia":[]},"Wrist":{"id":10000000725163,"materia":[]},"RingLeft":{"id":10000000725164,"materia":[]},"RingRight":{"id":10000000725164,"materia":[]}},"food":46003,"description":"","isSeparator":false,"relicStatMemory":{},"materiaMemory":{"Wrist":[[22800,[-1],[false]]],"Feet":[[22752,[-1,-1],[false,false]]]}},{"name":"---","items":{},"description":"","isSeparator":true,"relicStatMemory":{},"materiaMemory":{}},{"name":"2.40 - EW Relic","items":{"Weapon":{"id":40947,"materia":[],"relicStats":{"dhit":0,"crit":306,"tenacity":0,"determination":72,"skillspeed":306}},"Head":{"id":19375,"materia":[{"id":18019,"locked":false},{"id":18018,"locked":false}]},"Body":{"id":10000000725157,"materia":[]},"Hand":{"id":10000000725158,"materia":[]},"Legs":{"id":10000000725159,"materia":[]},"Feet":{"id":22752,"materia":[{"id":18018,"locked":false},{"id":18018,"locked":false}]},"Ears":{"id":10000000725161,"materia":[]},"Neck":{"id":10000000725162,"materia":[]},"Wrist":{"id":10000000725163,"materia":[]},"RingLeft":{"id":10000000725164,"materia":[]},"RingRight":{"id":10000000725164,"materia":[]}},"food":46003,"description":"For any of these EW Relic sets, they're meant to be \"close enough\". If you don't want to farm the specific gear listed, then don't. Just use a synced item that is at least ilvl 500+ with the same stat types.","isSeparator":false,"relicStatMemory":{},"materiaMemory":{}},{"name":"2.45 - EW Relic","items":{"Weapon":{"id":40947,"materia":[],"relicStats":{"dhit":0,"crit":306,"tenacity":0,"determination":72,"skillspeed":306}},"Head":{"id":10000000725156,"materia":[]},"Body":{"id":10000000725157,"materia":[]},"Hand":{"id":10000000725158,"materia":[]},"Legs":{"id":10000000725159,"materia":[]},"Feet":{"id":19301,"materia":[{"id":18019,"locked":false},{"id":18018,"locked":false}]},"Ears":{"id":10000000725161,"materia":[]},"Neck":{"id":10000000725162,"materia":[]},"Wrist":{"id":10000000725163,"materia":[]},"RingLeft":{"id":10000000725164,"materia":[]},"RingRight":{"id":10000000725164,"materia":[]}},"food":46003,"description":"","isSeparator":false,"relicStatMemory":{},"materiaMemory":{"Head":[[19375,[18019,18018],[false,false]]],"Feet":[[22752,[18018,18018],[false,false]]]}},{"name":"2.50 - EW Relic","items":{"Weapon":{"id":40947,"materia":[],"relicStats":{"dhit":0,"crit":306,"tenacity":72,"determination":306,"skillspeed":0}},"Head":{"id":10000000725156,"materia":[]},"Body":{"id":10000000725157,"materia":[]},"Hand":{"id":10000000725158,"materia":[]},"Legs":{"id":10000000725159,"materia":[]},"Feet":{"id":19301,"materia":[{"id":18019,"locked":false},{"id":18018,"locked":false}]},"Ears":{"id":10000000725161,"materia":[]},"Neck":{"id":10000000725162,"materia":[]},"Wrist":{"id":10000000725163,"materia":[]},"RingLeft":{"id":10000000725164,"materia":[]},"RingRight":{"id":10000000725164,"materia":[]}},"food":46003,"description":"","isSeparator":false,"relicStatMemory":{},"materiaMemory":{"Wrist":[[22800,[-1],[false]]],"Feet":[[22752,[-1,-1],[false,false]],[19301,[18019,18018],[false,false]]]}}],"level":70,"job":"GNB","partyBonus":5,"race":"Xaela","sims":[{"stub":"gnb-sheet-sim","settings":{"customSettings":{"usePotion":true,"fightTime":510,"pretendThatMicroclipsDontExist":true,"includeInExport":true},"buffConfig":{"jobs":[],"buffs":["Mug","Battle Litany","Brotherhood","Arcane Circle","Searing Light","Embolden","Starry Muse","Technical Finish","Battle Voice","Radiant Finale","Chain","Divination"]},"cycleSettings":{"useAutos":true,"totalTime":510,"cycles":0,"which":"totalTime","cutoffMode":"prorate-gcd"},"resultSettings":{"stdDevs":0}},"name":"GNB Sim"}],"itemDisplaySettings":{"minILvl":340,"maxILvl":345,"minILvlFood":740,"maxILvlFood":999,"higherRelics":true,"showNq":false,"showOneStatFood":false},"mfm":"retain_item","mfp":["skillspeed","crit","dhit","determination","tenacity"],"mfMinGcd":2.05,"ilvlSync":345,"customItems":[{"isUnique":false,"ilvl":470,"equipLvl":100,"largeMateriaSlots":2,"smallMateriaSlots":0,"materiaGrade":12,"stats":{"dhit":0,"mind":0,"strength":112,"spellspeed":0,"hp":0,"wdPhys":0,"piety":0,"determination":79,"intelligence":0,"dexterity":0,"crit":112,"vitality":114,"tenacity":0,"weaponDelay":0,"wdMag":0,"skillspeed":0},"respectCaps":true,"fakeId":10000000725156,"name":"Head - CRIT + DET","slot":"Head"},{"isUnique":false,"ilvl":470,"equipLvl":100,"largeMateriaSlots":2,"smallMateriaSlots":0,"materiaGrade":12,"stats":{"dhit":0,"mind":0,"strength":178,"spellspeed":0,"hp":0,"wdPhys":0,"piety":0,"determination":124,"intelligence":0,"dexterity":0,"crit":177,"vitality":182,"tenacity":0,"weaponDelay":0,"wdMag":0,"skillspeed":0},"respectCaps":true,"fakeId":10000000725157,"name":"Chest - CRIT + DET","slot":"Body"},{"isUnique":false,"ilvl":470,"equipLvl":100,"largeMateriaSlots":2,"smallMateriaSlots":0,"materiaGrade":12,"stats":{"dhit":0,"mind":0,"strength":112,"spellspeed":0,"hp":0,"wdPhys":0,"piety":0,"determination":79,"intelligence":0,"dexterity":0,"crit":112,"vitality":114,"tenacity":0,"weaponDelay":0,"wdMag":0,"skillspeed":0},"respectCaps":true,"fakeId":10000000725158,"name":"Hands - CRIT + DET","slot":"Hand"},{"isUnique":false,"ilvl":470,"equipLvl":100,"largeMateriaSlots":2,"smallMateriaSlots":0,"materiaGrade":12,"stats":{"dhit":0,"mind":0,"strength":178,"spellspeed":0,"hp":0,"wdPhys":0,"piety":0,"determination":124,"intelligence":0,"dexterity":0,"crit":177,"vitality":182,"tenacity":0,"weaponDelay":0,"wdMag":0,"skillspeed":0},"respectCaps":true,"fakeId":10000000725159,"name":"Legs - CRIT + DET","slot":"Legs"},{"isUnique":false,"ilvl":470,"equipLvl":100,"largeMateriaSlots":2,"smallMateriaSlots":0,"materiaGrade":12,"stats":{"dhit":0,"mind":0,"strength":112,"spellspeed":0,"hp":0,"wdPhys":0,"piety":0,"determination":79,"intelligence":0,"dexterity":0,"crit":112,"vitality":114,"tenacity":0,"weaponDelay":0,"wdMag":0,"skillspeed":0},"respectCaps":true,"fakeId":10000000725160,"name":"Feet - CRIT + DET","slot":"Feet"},{"isUnique":false,"ilvl":470,"equipLvl":100,"largeMateriaSlots":2,"smallMateriaSlots":0,"materiaGrade":12,"stats":{"dhit":0,"mind":0,"strength":88,"spellspeed":0,"hp":0,"wdPhys":0,"piety":0,"determination":62,"intelligence":0,"dexterity":0,"crit":88,"vitality":90,"tenacity":0,"weaponDelay":0,"wdMag":0,"skillspeed":0},"respectCaps":true,"fakeId":10000000725161,"name":"Ears - CRIT + DET","slot":"Ears"},{"isUnique":false,"ilvl":470,"equipLvl":100,"largeMateriaSlots":2,"smallMateriaSlots":0,"materiaGrade":12,"stats":{"dhit":0,"mind":0,"strength":88,"spellspeed":0,"hp":0,"wdPhys":0,"piety":0,"determination":62,"intelligence":0,"dexterity":0,"crit":88,"vitality":90,"tenacity":0,"weaponDelay":0,"wdMag":0,"skillspeed":0},"respectCaps":true,"fakeId":10000000725162,"name":"Neck - CRIT + DET","slot":"Neck"},{"isUnique":false,"ilvl":470,"equipLvl":100,"largeMateriaSlots":2,"smallMateriaSlots":0,"materiaGrade":12,"stats":{"dhit":0,"mind":0,"strength":88,"spellspeed":0,"hp":0,"wdPhys":0,"piety":0,"determination":62,"intelligence":0,"dexterity":0,"crit":88,"vitality":90,"tenacity":0,"weaponDelay":0,"wdMag":0,"skillspeed":0},"respectCaps":true,"fakeId":10000000725163,"name":"Wrist - CRIT + DET","slot":"Wrist"},{"isUnique":false,"ilvl":470,"equipLvl":100,"largeMateriaSlots":2,"smallMateriaSlots":0,"materiaGrade":12,"stats":{"dhit":0,"mind":0,"strength":88,"spellspeed":0,"hp":0,"wdPhys":0,"piety":0,"determination":62,"intelligence":0,"dexterity":0,"crit":88,"vitality":90,"tenacity":0,"weaponDelay":0,"wdMag":0,"skillspeed":0},"respectCaps":true,"fakeId":10000000725164,"name":"Ring - CRIT + DET","slot":"Ring"},{"isUnique":false,"ilvl":470,"equipLvl":100,"largeMateriaSlots":2,"smallMateriaSlots":0,"materiaGrade":12,"stats":{"dhit":0,"mind":0,"strength":88,"spellspeed":0,"hp":0,"wdPhys":0,"piety":0,"determination":0,"intelligence":0,"dexterity":0,"crit":88,"vitality":90,"tenacity":0,"weaponDelay":0,"wdMag":0,"skillspeed":62},"respectCaps":true,"fakeId":10000000725165,"name":"Neck - CRIT + SKS","slot":"Neck"},{"isUnique":false,"ilvl":470,"equipLvl":100,"largeMateriaSlots":2,"smallMateriaSlots":0,"materiaGrade":12,"stats":{"dhit":0,"mind":0,"strength":112,"spellspeed":0,"hp":0,"wdPhys":0,"piety":0,"determination":0,"intelligence":0,"dexterity":0,"crit":112,"vitality":114,"tenacity":0,"weaponDelay":0,"wdMag":0,"skillspeed":79},"respectCaps":true,"fakeId":10000000725166,"name":"Hands - CRIT + SKS","slot":"Hand"}],"customFoods":[],"timestamp":1747188436065,"isMultiJob":false,"specialStats":null}
